<?xml version="1.0" encoding="UTF-8" standalone="yes"?><configurationModel xmlns="ck.v20090401"><configuration xmlns=""><expression>TreeStructure</expression><transformation><name>selectAndMoveComponent</name><args>Company, org\softlang\company\Company.java</args></transformation></configuration><configuration xmlns=""><expression>JavaExorcismSPL</expression><transformation><name>createBuildEntries</name><args>JavaExorcismSPL</args></transformation></configuration><configuration xmlns=""><expression>TreeStructure</expression><transformation><name>createBuildEntries</name><args>TreeStructure</args></transformation></configuration><configuration xmlns=""><expression>TreeStructure</expression><transformation><name>selectAndMoveComponent</name><args>Component, org\softlang\company\Component.java</args></transformation></configuration><configuration xmlns=""><expression>TreeStructure</expression><transformation><name>selectAndMoveComponent</name><args>Container, org\softlang\company\Container.java</args></transformation></configuration><configuration xmlns=""><expression>TreeStructure</expression><transformation><name>selectAndMoveComponent</name><args>Department, org\softlang\company\Department.java</args></transformation></configuration><configuration xmlns=""><expression>TreeStructure</expression><transformation><name>selectAndMoveComponent</name><args>Employee, org\softlang\company\Employee.java</args></transformation></configuration><configuration xmlns=""><expression>TreeStructure</expression><transformation><name>selectAndMoveComponent</name><args>Subunit, org\softlang\company\Subunit.java</args></transformation></configuration><configuration xmlns=""><expression>TreeStructure</expression><transformation><name>selectAndMoveComponent</name><args>BeanFactory, org\softlang\company\factory\BeanFactory.java</args></transformation></configuration><configuration xmlns=""><expression>TreeStructure</expression><transformation><name>selectAndMoveComponent</name><args>Factory, org\softlang\company\factory\Factory.java</args></transformation></configuration><configuration xmlns=""><expression>TreeStructure</expression><transformation><name>selectAndMoveComponent</name><args>PojoFactory, org\softlang\company\factory\PojoFactory.java</args></transformation></configuration><configuration xmlns=""><expression>TreeStructure</expression><transformation><name>selectAndMoveComponent</name><args>CompanyImplBean, org\softlang\company\impl\bean\CompanyImpl.java</args></transformation></configuration><configuration xmlns=""><expression>TreeStructure</expression><transformation><name>selectAndMoveComponent</name><args>ComponentImplBean, org\softlang\company\impl\bean\ComponentImpl.java</args></transformation></configuration><configuration xmlns=""><expression>TreeStructure</expression><transformation><name>selectAndMoveComponent</name><args>ContainerImplBean, org\softlang\company\impl\bean\ContainerImpl.java</args></transformation></configuration><configuration xmlns=""><expression>TreeStructure</expression><transformation><name>selectAndMoveComponent</name><args>DepartmentImplBean, org\softlang\company\impl\bean\DepartmentImpl.java</args></transformation></configuration><configuration xmlns=""><expression>TreeStructure</expression><transformation><name>selectAndMoveComponent</name><args>EmployeeImplBean, org\softlang\company\impl\bean\EmployeeImpl.java</args></transformation></configuration><configuration xmlns=""><expression>TreeStructure</expression><transformation><name>selectAndMoveComponent</name><args>CompanyImplPojo, org\softlang\company\impl\pojo\CompanyImpl.java</args></transformation></configuration><configuration xmlns=""><expression>TreeStructure</expression><transformation><name>selectAndMoveComponent</name><args>ComponentImplPojo, org\softlang\company\impl\pojo\ComponentImpl.java</args></transformation></configuration><configuration xmlns=""><expression>TreeStructure</expression><transformation><name>selectAndMoveComponent</name><args>ContainerImplPojo, org\softlang\company\impl\pojo\ContainerImpl.java</args></transformation></configuration><configuration xmlns=""><expression>TreeStructure</expression><transformation><name>selectAndMoveComponent</name><args>DepartmentImplPojo, org\softlang\company\impl\pojo\DepartmentImpl.java</args></transformation></configuration><configuration xmlns=""><expression>TreeStructure</expression><transformation><name>selectAndMoveComponent</name><args>EmployeeImplPojo, org\softlang\company\impl\pojo\EmployeeImpl.java</args></transformation></configuration><configuration xmlns=""><expression>TreeStructure</expression><transformation><name>selectAndMoveComponent</name><args>ReturningVisitor, org/softlang/visitor/ReturningVisitor.java</args></transformation></configuration><configuration xmlns=""><expression>TreeStructure</expression><transformation><name>selectAndMoveComponent</name><args>VoidVisitor, org/softlang/visitor/VoidVisitor.java</args></transformation></configuration><configuration xmlns=""><expression>TreeStructure</expression><transformation><name>selectAndMoveComponent</name><args>ObservableSimpleList, org/softlang/util/ObservableSimpleList.java</args></transformation></configuration><configuration xmlns=""><expression>TreeStructure</expression><transformation><name>selectAndMoveComponent</name><args>SimpleList, org/softlang/util/SimpleList.java</args></transformation></configuration><configuration xmlns=""><expression>TreeStructure</expression><transformation><name>selectAndMoveComponent</name><args>SimpleLinkedList, org/softlang/util/SimpleLinkedList.java</args></transformation></configuration><configuration xmlns=""><expression>TreeStructure</expression><transformation><name>selectAndMoveComponent</name><args>AddToList, org/softlang/util/AddToList.java</args></transformation></configuration><configuration xmlns=""><expression>TreeStructure</expression><transformation><name>selectAndMoveComponent</name><args>ChangeList, org/softlang/util/ChangeList.java</args></transformation></configuration><configuration xmlns=""><expression>TreeStructure</expression><transformation><name>selectAndMoveComponent</name><args>RemoveFromList, org/softlang/util/RemoveFromList.java</args></transformation></configuration><configuration xmlns=""><expression>Logging</expression><transformation><name>createBuildEntries</name><args>Logging</args></transformation></configuration><configuration xmlns=""><expression>Logging</expression><transformation><name>selectAndMoveComponent</name><args>Logging, org/softlang/features/Logging.java</args></transformation></configuration><configuration xmlns=""><expression>AccessControl</expression><transformation><name>createBuildEntries</name><args>AccessControl</args></transformation></configuration><configuration xmlns=""><expression>AccessControl</expression><transformation><name>selectAndMoveComponent</name><args>AccessControl, org/softlang/proxy/AccessControl.java</args></transformation></configuration><configuration xmlns=""><expression>AccessControl</expression><transformation><name>selectAndMoveComponent</name><args>ProxyCompany,  org/softlang/proxy/ProxyCompany.java</args></transformation></configuration><configuration xmlns=""><expression>AccessControl</expression><transformation><name>selectAndMoveComponent</name><args>ProxyDepartment, org/softlang/proxy/ProxyDepartment.java</args></transformation></configuration><configuration xmlns=""><expression>AccessControl</expression><transformation><name>selectAndMoveComponent</name><args>ProxyEmployee, org/softlang/proxy/ProxyEmployee.java</args></transformation></configuration><configuration xmlns=""><expression>TypeDrivenTransformation</expression><transformation><name>createBuildEntries</name><args>TypeDrivenTransformation</args></transformation></configuration><configuration xmlns=""><expression>TypeDrivenTransformation</expression><transformation><name>selectAndMoveComponent</name><args>Batch, org/softlang/command/Batch.java</args></transformation></configuration><configuration xmlns=""><expression>TypeDrivenTransformation</expression><transformation><name>selectAndMoveComponent</name><args>Command, org/softlang/command/Command.java</args></transformation></configuration><configuration xmlns=""><expression>TypeDrivenTransformation</expression><transformation><name>selectAndMoveComponent</name><args>CutCompany, org/softlang/command/CutCompany.java</args></transformation></configuration><configuration xmlns=""><expression>TypeDrivenTransformation</expression><transformation><name>selectAndMoveComponent</name><args>CutEmployee, org/softlang/command/CutEmployee.java</args></transformation></configuration><configuration xmlns=""><expression>TypeDrivenTransformation</expression><transformation><name>selectAndMoveComponent</name><args>Reducer, org/softlang/template/Reducer.java</args></transformation></configuration><configuration xmlns=""><expression>TypeDrivenTransformation</expression><transformation><name>selectAndMoveComponent</name><args>Walker, org/softlang/template/Walker.java</args></transformation></configuration><configuration xmlns=""><expression>TypeDrivenTransformation</expression><transformation><name>selectAndMoveComponent</name><args>OrderedCut, org/softlang/features/OrderedCut.java</args></transformation></configuration><configuration xmlns=""><expression>TypeDrivenTransformation</expression><transformation><name>selectAndMoveComponent</name><args>SimpleCut, org/softlang/features/SimpleCut.java</args></transformation></configuration><configuration xmlns=""><expression>TypeDrivenTransformation</expression><transformation><name>selectAndMoveComponent</name><args>TotalReducer, org/softlang/features/TotalReducer.java</args></transformation></configuration><configuration xmlns=""><expression>TypeDrivenTransformation</expression><transformation><name>selectAndMoveComponent</name><args>TotalWalker, org/softlang/features/TotalWalker.java</args></transformation></configuration><configuration xmlns=""><expression>TypeDrivenTransformation</expression><transformation><name>selectAndMoveComponent</name><args>Monoid, org/softlang/util/Monoid.java</args></transformation></configuration><configuration xmlns=""><expression>TypeDrivenTransformation</expression><transformation><name>selectAndMoveComponent</name><args>AddDoubles, org/softlang/util/AddDoubles.java</args></transformation></configuration><configuration xmlns=""><expression>TypeDrivenTransformation</expression><transformation><name>selectAndMoveComponent</name><args>MaxDoubles, org/softlang/util/MaxDoubles.java</args></transformation></configuration><configuration xmlns=""><expression>TypeDrivenTransformation</expression><transformation><name>selectAndMoveComponent</name><args>Walker, org/softlang/template/Walker.java</args></transformation></configuration></configurationModel>